LICENSE
README.md
setup.py
pyortho/__init__.py
pyortho/divne.py
pyortho/drr3d.py
pyortho/localortho.py
pyortho/localsimi.py
pyortho/snr.py
pyortho_win.egg-info/PKG-INFO
pyortho_win.egg-info/SOURCES.txt
pyortho_win.egg-info/dependency_links.txt
pyortho_win.egg-info/not-zip-safe
pyortho_win.egg-info/requires.txt
pyortho_win.egg-info/top_level.txt