Metadata-Version: 2.1
Name: pyortho-win
Version: 0.0.1
Summary: Pyortho-win: A python package for local signal-and-noise orthogonalization and local similarity calculation (windows version)
Home-page: https://github.com/aaspip/pyortho-win
Author: pyortho developing team
Author-email: chenyk2016@gmail.com
License: GNU General Public License, Version 3 (GPLv3)
Keywords: seismology,exploration seismology,array seismology,denoising,science,orthogonalization,local orthogonalization,local similarity,signal-to-noise ratio,damped rank reduction method
Classifier: Development Status :: 4 - Beta
Classifier: Intended Audience :: Developers
Classifier: Intended Audience :: Science/Research
Classifier: Operating System :: Unix
Classifier: Operating System :: POSIX
Classifier: Operating System :: Microsoft :: Windows
Classifier: Programming Language :: Python
Classifier: Programming Language :: Python :: 3.8
Classifier: Programming Language :: Python :: Implementation :: CPython
Classifier: Topic :: Scientific/Engineering
Classifier: Topic :: Scientific/Engineering :: Physics
Classifier: License :: OSI Approved :: GNU General Public License v3 (GPLv3)
Provides-Extra: docs
License-File: LICENSE
